{
  "签号": "第一签",
  "签名": "宋太祖登基",
  "签文类型": "吉胜无疑之兆",
  "卦象": "上上之卦",
  "生肖": "申猴",
  "签文简介": {
    "戏文": "公元960年，后周大将赵匡胤黄袍加身，起陈桥兵变，废后周帝，改国号宋，定都东京，继而结束五代十国割据局面，一统江山。",
    "诗曰": "一箭射红心，人人说好音；日长鸡唱午，真火炼真金。",
    "内兆": "飞龙变化"
  },
  "家宅运势": {
    "签文": "三阳交泰转洪钓，瑞气盈门百事新。岁秽时丰财禄旺，又添人口许相亲。",
    "解曰": "吉宅人口之卦可得喜气，但防夏月疾难是非涉财火厄，皆因厝前受煞冲伤，吓佛祖令旗安门上祭化又嫌水道不美，有利宜修整，则居住平安。"
  },
  "岁君签": {
    "总诗": "飞龙变化喜逢时，此日升腾果遂期。某望求财皆得利，求官进职更无疑。",
    "年龄运势": [
      {
        "年龄": "1-3岁",
        "男": "小孩根苗足养，八字成格旺益上人并茂，夏月小疾无妨，吉星守命平安。",
        "女": "小女根基足养，有旺益上人并茂，虽有小疾无妨，吉星守命出入平安。"
      },
      {
        "年龄": "4-7岁",
        "男": "小儿运限叶吉，生性天真活泼，夏月宜知避暑，小皮疾无妨，吉星守命平安。",
        "女": "小女运限顺遂，活泼伶俐，旺益上人，夏月小疾无妨，吉星守命平安。"
      },
      {
        "年龄": "8-12岁",
        "男": "小儿今年交上美运，伶俐天真，可入学校读书，定卜进步。",
        "女": "小女现年交上美运，有旺益上人并茂，吉星守命平安。"
      },
      {
        "年龄": "13-15岁",
        "男": "童造上运亨通聪明开窍，培养入学读书，定卜进步。",
        "女": "小女之卦运度顺遂，各事伶俐精通旺益上人。"
      },
      {
        "年龄": "16-17岁",
        "男": "祥造步运亨通，如飞龙变化，做事通能特达，宜多学文化，远景无限。",
        "女": "玉造现年交上美运，如飞龙变化，八字清秀技巧助益家庭。"
      },
      {
        "年龄": "18-29岁",
        "男": "英造步运亨通，如飞龙变化，奇才特达，年轻有为，有贵人辅助。",
        "女": "玉造行运交泰，如飞龙变化，各事贤玉，多学艺业。"
      },
      {
        "年龄": "30-55岁",
        "男": "乾造步运亨通，如飞龙变化，做事老练，有贵人辅助。",
        "女": "坤造行运交泰，如飞龙变化，娴熟智慧。"
      },
      {
        "年龄": "56-69岁",
        "男": "台造步运亨通，如飞龙变化，为人老练忠诚。",
        "女": "坤造行运交泰，如飞龙变化，底子有旺宜家庭。"
      },
      {
        "年龄": "70岁以上",
        "男": "福造老运虽绵长，但卦旺须防跌伤之厄。",
        "女": "妇造老运旺益子孙，但防暗疾风气。"
      }
    ]
  },
  "生意": {
    "生意": "春月生意欲失财，夏月财利丝丝来。待到秋冬两季节，壮胆经营利路开。",
    "生意解曰": "生意初时有阻，交易宜正直，刻苦经营，候五、八、十一月返运，可得厚财利。",
    "开铺": "开铺签文叶吉，各事宜小心，可以成功。",
    "合伙": "多人多福，各人同心协力经营，可得厚财利。",
    "置货": "置货须立胆智，初时价败，但见机可得厚利。"
  },
  "出外": {
    "出外": "初有阻隔，但三、五、八月往外，有贵人扶助，名利双全。"
  },
  "谋望求财": {
    "谋望": "冲霄志气上心头，君子安宁久困穷。岁稔时丰财禄旺，万人头上逞英雄。",
    "谋望解曰": "谋事初有阻隔，但刻苦谋之到底可成。",
    "求财": "正财初有波折，三、五、八月返运可得大利，偏财须大胆谨慎。"
  },
  "学艺功名": {
    "学艺": "签文叶吉，专心学习，有贵人扶助，定卜成功。",
    "功名": "功名多波折，但最终可成功。"
  },
  "行舟六畜": {
    "行舟": "行舟顺风，秋后可得大利。",
    "六畜": "饲养六畜能平安。",
    "猪羊": "猪羊养殖顺利，可得厚利。",
    "草龙": "水草调和，养之兴旺。",
    "三鸟": "精心饲养，有利可收。",
    "田蚕": "四季雨水大吉。"
  },
  "移徙": {
    "移徙": "移徙吉，宜请华光爷镇宅。"
  },
  "行人": {
    "解曰": "行人在外有贵人扶助，五、八、十一月有消息。",
    "签文": "卦得飞龙莫问亲，千山万水受艰辛。"
  },
  "婚姻": {
    "解曰": "婚姻天配良缘，情投意合，白头偕老。",
    "签文": "世间天理定婚姻，天配良缘。"
  },
  "官讼": {
    "解曰": "宜和不宜告，赢官司可能输财。",
    "签文": "未发文书不要陈。"
  },
  "失物": {
    "解曰": "向南方向寻找，定有音讯。",
    "签文": "偶失货物莫怨天。"
  },
  "占病": {
    "解曰": "老年多风湿气咳，青壮年多肾疾焦躁。",
    "签文": "焚香祷告，修德行善。"
  },
  "其他": {
    "灶君": "灶位分金合课，但需避窗煞。",
    "阳基": "阳宅财丁可旺，但青龙方向有煞。",
    "六甲": "六甲生男，合家欢喜。",
    "子息": "子息先花后果。",
    "祖山": "祖山气脉足，修整可旺财丁。",
    "青草": "墓地气脉足旺，但初时有阻。"
  }
}